setch/__init__.py
set_ch-10.dist-info/LICENSE
set_ch-10.dist-info/METADATA
set_ch-10.dist-info/WHEEL
set_ch-10.dist-info/top_level.txt
set_ch-10.dist-info/RECORD
